menglingtool_handle/__init__.py
menglingtool_handle/analysis.py
menglingtool_handle/make.py
menglingtool_handle/structure.py
menglingtool_handle/__structure__/dynamic_cache.py
menglingtool_handle/__structure__/goods.py
menglingtool_handle/__structure__/link.py
menglingtool_handle/__structure__/ring_twoway_link.py
menglingtool_handle/__structure__/synchronize_iterate.py
menglingtool_handle/__structure__/synchronize_many.py
menglingtool_handle-1.0.1.dist-info/METADATA
menglingtool_handle-1.0.1.dist-info/WHEEL
menglingtool_handle-1.0.1.dist-info/top_level.txt
menglingtool_handle-1.0.1.dist-info/RECORD
